README.md
setup.py
zuanfeng/__init__.py
zuanfeng/zuanfeng.py
zuanfeng.egg-info/PKG-INFO
zuanfeng.egg-info/SOURCES.txt
zuanfeng.egg-info/dependency_links.txt
zuanfeng.egg-info/requires.txt
zuanfeng.egg-info/top_level.txt