Metadata-Version: 1.0
Name: zuanfeng
Version: 0.0.3
Summary: zuanfeng captain sdk
Home-page: http://lazybios.com
Author: lazybios
Author-email: lazybios@gmail.com
License: MIT Licence
Keywords: pip,zuanfeng,xiaozuanfeng,zuanfengxiaojiang,zf
Platform: any
